{"name": "Click on highlighted area for more information on patient variant.",
  "classifier":"n/a",
"children": [{
  "name": "p.L858R",
  "Response":"n/a",
  "Approach":"n/a",
  "Evidence":"n/a",
  "classifier":"variant",
  "children": [{
    "name": "Gefitinib",
    "Response":"Sensitive",
    "Approach":"EGFR Inhibitor 1st gen",
    "Evidence":"Actionable",
    "size":50,
    "classifier":"drug-name"
    }
  , {
    "name": "Erlotinib",
    "Response":"Sensitive",
    "Approach":"EGFR Inhibitor 1st gen & EGFR Inhibitor (Pan)",
    "Evidence":"Actionable",
    "size":50,
    "classifier":"drug-name"
  }, {
    "name": "Aftanib",
    "Response":"Sensitive",
    "Approach":"HER Inhibitor (Pan) & EGFR Inhibitor (Pan) & EGFR Inhibitor 2nd gen",
    "Evidence":"Actionable",
    "size":50,
    "classifier":"drug-name"
  },
 {
  "name": "AZD9291",
  "Response":"Sensitive",
  "Approach":"EGFR Inhibitor 3rd gen",
  "Evidence":"Actionable",
  "size":50,
  "classifier":"drug-name"
  }, {
    "name": "Dacomitinib",
    "Response":"Sensitive",
    "Approach":"EGFR Inhibitor 2nd gen & HER Inhibitor (Pan)",
    "Evidence":"Actionable",
    "size":50,
    "classifier":"drug-name"
  },
{
  "name": "Icotinib",
  "Response":"Sensitive",
  "Approach":"EGFR Inhibitor 1st gen",
  "Evidence":"Actionable",
  "size":50,
  "classifier":"drug-name"
  }, {
    "name": "CO1686",
    "Response":"Sensitive",
    "Approach":"EGFR Inhibitor 3rd gen",
    "Evidence":"Actionable",
    "size":50,
    "classifier":"drug-name"
  },
{
  "name": "TAE226",
  "Response":"Sensitive",
  "Approach":"EGFR Inhibitor 3rd gen",
  "Evidence":"Actionable",
  "size":50,
  "classifier":"drug-name"
  },{
  "name": "EGF816",
  "Response":"Sensitive",
  "Approach":"EGFR Inhibitor 3rd gen",
  "Evidence":"Actionable",
  "size":50,
  "classifier":"drug-name"

}]},
{
  "name": "p.E746_A750del",
  "Response":"n/a",
  "Approach":"n/a",
  "Evidence":"n/a",
  "classifier":"variant",
  "children": [{
    "name": "Gefitinib",
    "Response":"Sensitive",
    "Approach":"EGFR Inhibitor 1st gen",
    "Evidence":"Actionable",
    "size":50,
    "classifier":"drug-name"
  },
   {
    "name": "Erlotinib",
    "Response":"Sensitive",
    "Approach":"EGFR Inhibitor 1st gen    EGFR Inhibitor (Pan)",
    "Evidence":"Actionable",
    "size":50,
    "classifier":"drug-name"
  }, {
    "name": "Aftanib",
    "Response":"Sensitive",
    "Approach":"HER Inhibitor (Pan) EGFR Inhibitor (Pan) EGFR Inhibitor 2nd gen",
    "Evidence":"Actionable",
    "size":50,
    "classifier":"drug-name"
  },
 {
  "name": "Lapatinib",
  "Response":"Resistant",
  "Approach":"EGFR Inhibitor (Pan)",
  "Evidence":"Actionable",
  "size":50,
  "classifier":"drug-name"
  }, {
    "name": "Dacomitinib",
    "Response":"Sensitive",
    "Approach":"EGFR Inhibitor 2nd gen    HER Inhibitor (Pan)",
    "Evidence":"Actionable",
    "size":50,
    "classifier":"drug-name"
  },
 {
    "name": "Icotinib",
    "Response":"Sensitive",
    "Approach":"EGFR Inhibitor 1st gen",
    "Evidence":"Actionable",
    "size":50,
    "classifier":"drug-name"
    }, {
      "name": "Erlotinib+\nGanestepib",
      "Response":"Sensitive",
      "Approach":"EGFR Inhibitor 1st gen    EGFR Inhibitor Pan",
      "Evidence":"Actionable",
      "size":50,
      "classifier":"drug-name"
    },
  {
    "name": "P5-05212384",
    "Response":"Sensitive",
    "Approach":"",
    "Evidence":"Actionable",
    "size":50,
    "classifier":"drug-name"
    },{
    "name": "ER2",
    "Response":"Sensitive",
    "Approach":"",
    "Evidence":"Actionable",
    "size":50,
    "classifier":"drug-name"
}]},{
  "name": "p.E746_A750delELREA",
  "Response":"n/a",
  "Approach":"n/a",
  "Evidence":"n/a",
  "classifier":"variant",
  "children": [{
    "name": "unknown",
    "Response":"n/a",
    "Approach":"",
    "Evidence":"",
    "size":50,
    "classifier":"drug-name"
  }]
},
{
  "name": "p.T790M",
   "Response":"n/a",
    "Approach":"n/a",
    "Evidence":"n/a",
  "classifier":"variant",
  "children": [{
    "name": "Erlotinib",
    "Response":"Resistant",
    "classifier":"drug-name",
    "Approach":"",
    "Evidence":"Actionable",
    "size":50
  },
   {
    "name": "Aftanib",
    "classifier":"drug-name",
    "Response":"Predicted-Resistant",
    "Approach":"HER Inhibitor (Pan), EGFR Inhibitor (Pan), EGFR Inhibitor 2nd gen",
    "Evidence":"Actionable",
    "size":50
  },
 {
  "name": "AZD9291",
  "classifier":"drug-name",
  "Response":"Sensitive",
  "Approach":"EGFR Inhibitor 3rd gen",
  "Evidence":"Actionable",
  "size":50
  }, {
    "name": "Epitinib",
    "classifier":"drug-name",
    "Response":"Predicted-Sensitive",
    "Approach":"",
    "Evidence":"Actionable",
    "size":50
  }]},

{  "Position": 790,
  "CMutation": "c.2369C>T",
  "name": "p.T790M",
  "ID": 6240,
  "Count": 34,
  "Type": "Substitution - Missense",
  "Response": "n/a",
  "Approach": "n/a",
  "Evidence": "n/a",
  "classifier":"variant",
  "children":[{
  "name": "Erlotinib",
  "Response": "Resistant",
  "Approach": "n/a",
  "Evidence": "Actionable",
  "size": 50,
  "classifier": "drug-name"},{
  "name": "Aftanib",
  "Response": "Predicted-Resistant",
  "Approach": "HER Inhibitor (Pan), EGFR Inhibitor (Pan), EGFR Inhibitor 2nd gen",
  "Evidence": "Actionable",
  "size": 50,
  "classifier": "drug-name"},{
  "name": "AZD9291",
  "Response": "Sensitive",
  "Approach": "EGFR Inhibitor 3rd gen",
  "Evidence": "Actionable",
  "size": 50,
  "classifier": "drug-name"},{
  "name": "Epitinib",
  "Response": "Predicted-Sensitive",
  "Approach": "",
  "Evidence": "Actionable",
  "size": 50,
  "classifier": "drug-name"}]},{
    "Position": 768,
    "CMutation": "c.?",
    "name": "p.S768I",
    "ID": 18486,
    "Count": 30,
    "Type": "Substitution - Missense",
    "Response": "n/a",
    "Approach": "n/a",
    "Evidence": "n/a",
    "classifier":"variant",
    "children":[{
    "name": "Aftanib",
    "Response": "Sensitive",
    "Approach": "EGFR Inhibitor (Pan), EGFR Inhibitor 2nd gen, HER Inhibitor (Pan)",
    "Evidence": "Actionable",
    "size": 50,
    "classifier": "drug-name"},{
    "name": "Erlotinib",
    "Response": "Decreased-Response",
    "Approach": "EGFR Inhibitor 1st gen, EGFR Inhibitor (Pan)",
    "Evidence": "Actionable",
    "size": 50,
    "classifier": "drug-name"}]},{
      "Position": 719,
      "CMutation": "c.?",
      "name": "p.G719S",
      "ID": 13983,
      "Count": 30,
      "Type": "Substitution - Missense",
      "Response": "n/a",
      "Approach": "n/a",
      "Evidence": "n/a",
      "classifier":"variant",
      "children":[{
      "name": "Erlotinib",
      "Response": "Sensitive",
      "Approach": "EGFR Inhibitor 1st gen, EGFR Inhibitor (Pan)",
      "Evidence": "Actionable",
      "size": 50,
      "classifier": "drug-name"},{
      "name": "Gefitinib",
      "Response": "Sensitive",
      "Approach": "EGFR Inhibitor 1st gen",
      "Evidence": "Actionable",
      "size": 50,
      "classifier": "drug-name"}]},  {
          "Position": 719,
          "CMutation": "c.?",
          "name": "p.G719?",
          "ID": 85997,
          "Count": 29,
          "Type": "Substitution - Missense",
          "Response": "n/a",
          "Approach": "n/a",
          "Evidence": "n/a",
          "classifier":"variant",
          "children":[{
          "name": "unknown",
          "Response": "n/a",
          "Approach": "n/a",
          "Evidence": "n/a",
          "size": 50,
          "classifier": "drug-name"}]},
            {
              "Position": 747,
              "CMutation": "c.?",
              "name": "p.L747_A750>P",
              "ID": 13562,
              "Count": 26,
              "Type": "Complex - deletion inframe",
              "Response": "n/a",
              "Approach": "n/a",
              "Evidence": "n/a",
              "classifier":"variant",
              "children":[{
              "name": "unknown",
              "Response": "n/a",
              "Approach": "n/a",
              "Evidence": "n/a",
              "size": 50,
              "classifier": "drug-name"}]},

            {
              "Position": 746,
              "CMutation": "c.2237_2255>T",
              "name": "p.E746_S752>V",
              "ID": 12384,
              "Count": 24,
              "Type": "Complex - deletion inframe",
              "Response": "n/a",
              "Approach": "n/a",
              "Evidence": "n/a",
              "classifier":"variant",
              "children":[{
              "name": "unknown",
              "Response": "n/a",
              "Approach": "n/a",
              "Evidence": "n/a",
              "size": 50,
              "classifier": "drug-name"}]},

            {
              "Position": 747,
              "CMutation": "c.2240_2254del15",
              "name": "p.L747_T751delLREAT",
              "ID": 12369,
              "Count": 22,
              "Type": "Deletion - In frame",
              "Response": "n/a",
              "Approach": "n/a",
              "Evidence": "n/a",
              "classifier":"variant",
              "children":[{
              "name": "unknown",
              "Response": "n/a",
              "Approach": "n/a",
              "Evidence": "n/a",
              "size": 50,
              "classifier": "drug-name"}]},

            {
              "Position": 861,
              "CMutation": "c.2582T>A",
              "name": "p.L861Q",
              "ID": 6213,
              "Count": 22,
              "Type": "Substitution - Missense",
              "Response": "n/a",
              "Approach": "n/a",
              "Evidence": "n/a",
              "classifier":"variant",
              "children":[{
              "name": "Aftanib",
              "Response": "Sensitive",
              "Approach": "EGFR Inhibitor (Pan), EGFR Inhibitor 2nd gen, HER Inhibitor (Pan)",
              "Evidence": "Actionable",
              "size": 50,
              "classifier": "drug-name"},{
              "name": "Erlotinib",
              "Response": "Sensitive",
              "Approach": "EGFR Inhibitor 1st gen, EGFR Inhibitor (Pan)",
              "Evidence": "Actionable",
              "size": 50,
              "classifier": "drug-name"}]}
]}
